{
  "version": "7",
  "dialect": "postgresql",
  "entries": [
    {
      "idx": 0,
      "version": "7",
      "when": 1782963777871,
      "tag": "0000_baseline",
      "breakpoints": true
    },
    {
      "idx": 1,
      "version": "7",
      "when": 1783039083384,
      "tag": "0001_user_profiles",
      "breakpoints": true
    },
    {
      "idx": 2,
      "version": "7",
      "when": 1783043524302,
      "tag": "0002_user_imported_songs",
      "breakpoints": true
    },
    {
      "idx": 3,
      "version": "7",
      "when": 1783092059634,
      "tag": "0003_vengeful_cerise",
      "breakpoints": true
    },
    {
      "idx": 4,
      "version": "7",
      "when": 1783094667731,
      "tag": "0004_worthless_radioactive_man",
      "breakpoints": true
    }
  ]
}